yolov4/__init__.py
yolov4/__main__.py
yolov4/custom_loader.py
yolov4/demo.py
yolov4/cfg/yolov3-tiny.cfg
yolov4/cfg/yolov3.cfg
yolov4/cfg/yolov4-custom.cfg
yolov4/cfg/yolov4-sam-mish.cfg
yolov4/cfg/yolov4-tiny.cfg
yolov4/cfg/yolov4.cfg
yolov4/data/coco.names
yolov4/data/voc.names
yolov4/tool/__init__.py
yolov4/tool/base.py
yolov4/tool/camera.py
yolov4/tool/class_names.py
yolov4/tool/coco_annotation.py
yolov4/tool/config.py
yolov4/tool/darknet2onnx.py
yolov4/tool/darknet2pytorch.py
yolov4/tool/onnx2tensorflow.py
yolov4/tool/region_loss.py
yolov4/tool/torch_utils.py
yolov4/tool/utils.py
yolov4/tool/utils_iou.py
yolov4/tool/utils_iou_test.py
yolov4/tool/weights.py
yolov4/tool/yolo_layer.py
wf_pytorch_yolo_v4-0.2.2.dist-info/METADATA
wf_pytorch_yolo_v4-0.2.2.dist-info/WHEEL
wf_pytorch_yolo_v4-0.2.2.dist-info/entry_points.txt
wf_pytorch_yolo_v4-0.2.2.dist-info/top_level.txt
wf_pytorch_yolo_v4-0.2.2.dist-info/RECORD
