Metadata-Version: 2.1
Name: wf-pytorch-yolo-v4
Version: 0.2.2
Summary: Forked version of a minimal PyTorch implementation of YOLOv4
Home-page: https://github.com/WildflowerSchools/pytorch-YOLOv4
Author: Tianxiaomo; Benjamin Jaffe-Talberg
Author-email: ben.talberg@wildflowerschools.org
License: UNKNOWN
Keywords: yolo,yolov4,pytorch
Platform: UNKNOWN
Classifier: Intended Audience :: Developers
Classifier: License :: OSI Approved :: Apache Software License
Classifier: Operating System :: OS Independent
Classifier: Programming Language :: Python
Requires-Python: >=3
Requires-Dist: numpy (>=1.22)
Requires-Dist: torch (>=1.4.0)
Requires-Dist: tensorboardX (>=2.0)
Requires-Dist: scikit-image (>=0.16.2)
Requires-Dist: matplotlib (>=2.2.3)
Requires-Dist: tqdm (>=4.43.0)
Requires-Dist: easydict (>=1.9)
Requires-Dist: Pillow (>=9.0.1)
Requires-Dist: opencv-python
Requires-Dist: wf-pycocotools (>=2.0.1.1)
Requires-Dist: googledrivedownloader (>=0.4)
